dxlbootstrap/__init__.py
dxlbootstrap/__main__.py
dxlbootstrap/_cli.py
dxlbootstrap/_compat.py
dxlbootstrap/_exceptions.py
dxlbootstrap/_version.py
dxlbootstrap/app.py
dxlbootstrap/client.py
dxlbootstrap/util.py
dxlbootstrap/generate/__init__.py
dxlbootstrap/generate/app.py
dxlbootstrap/generate/core/__init__.py
dxlbootstrap/generate/core/component.py
dxlbootstrap/generate/core/template.py
dxlbootstrap/generate/templates/__init__.py
dxlbootstrap/generate/templates/app/__init__.py
dxlbootstrap/generate/templates/app/template.py
dxlbootstrap/generate/templates/app/static/Dockerfile.tmpl
dxlbootstrap/generate/templates/app/static/LICENSE.tmpl
dxlbootstrap/generate/templates/app/static/MANIFEST.in.tmpl
dxlbootstrap/generate/templates/app/static/README.md.tmpl
dxlbootstrap/generate/templates/app/static/README.tmpl
dxlbootstrap/generate/templates/app/static/__init__.py
dxlbootstrap/generate/templates/app/static/clean.py.tmpl
dxlbootstrap/generate/templates/app/static/dist.py.tmpl
dxlbootstrap/generate/templates/app/static/setup.py.tmpl
dxlbootstrap/generate/templates/app/static/app/__init__.py
dxlbootstrap/generate/templates/app/static/app/__init__.py.blank.tmpl
dxlbootstrap/generate/templates/app/static/app/__init__.py.tmpl
dxlbootstrap/generate/templates/app/static/app/__main__.py.tmpl
dxlbootstrap/generate/templates/app/static/app/_version.py.tmpl
dxlbootstrap/generate/templates/app/static/app/app.py.tmpl
dxlbootstrap/generate/templates/app/static/app/eventhandlers.py.tmpl
dxlbootstrap/generate/templates/app/static/app/requesthandlers.py.tmpl
dxlbootstrap/generate/templates/app/static/app/code/events_event_callback.code.tmpl
dxlbootstrap/generate/templates/app/static/app/code/pass.code.tmpl
dxlbootstrap/generate/templates/app/static/app/code/register_event_handler.code.tmpl
dxlbootstrap/generate/templates/app/static/app/code/register_event_handler_def.code.tmpl
dxlbootstrap/generate/templates/app/static/app/code/register_services_def.code.tmpl
dxlbootstrap-0.2.2.dist-info/LICENSE
dxlbootstrap-0.2.2.dist-info/METADATA
dxlbootstrap-0.2.2.dist-info/WHEEL
dxlbootstrap-0.2.2.dist-info/entry_points.txt
dxlbootstrap-0.2.2.dist-info/top_level.txt
dxlbootstrap-0.2.2.dist-info/RECORD
